quart_depends/__about__.py
quart_depends/__init__.py
quart_depends/binders.py
quart_depends/extension.py
quart_depends/wiring.py
quart_depends-1.0.1.dist-info/LICENSE.txt
quart_depends-1.0.1.dist-info/METADATA
quart_depends-1.0.1.dist-info/WHEEL
quart_depends-1.0.1.dist-info/top_level.txt
quart_depends-1.0.1.dist-info/RECORD
